testjy241008
