Metadata-Version: 2.1
Name: testjy241008
Version: 0.0.3
Summary: PYPI tutorial package creation written by TeddyNote
Home-page: https://github.com/JeeYz/like_g_orwell
Author: jeeyz
Author-email: like.g.orwell@gmail.com
Classifier: Programming Language :: Python :: 3.6
Classifier: Programming Language :: Python :: 3.7
Classifier: Programming Language :: Python :: 3.8
Classifier: Programming Language :: Python :: 3.9
Classifier: Programming Language :: Python :: 3.10
Classifier: Programming Language :: Python :: 3.11
Requires-Python: >=3.6
Requires-Dist: pytest
